LICENSE.md
MANIFEST.in
README.md
setup.py
github_manager.egg-info/PKG-INFO
github_manager.egg-info/SOURCES.txt
github_manager.egg-info/dependency_links.txt
github_manager.egg-info/entry_points.txt
github_manager.egg-info/requires.txt
github_manager.egg-info/top_level.txt
gitman/__init__.py
gitman/gitman.py
gitman/locales/en_US.py